cal_pkg/__init__.py
cal_pkg/four.py
print_pkg/__init__.py
print_pkg/print2_module.py
njmodule-1.2.dist-info/METADATA
njmodule-1.2.dist-info/WHEEL
njmodule-1.2.dist-info/top_level.txt
njmodule-1.2.dist-info/RECORD
