Metadata-Version: 2.1
Name: njmodule
Version: 1.2
Summary: DB module
Home-page: https://github.com/rampart81/pyquibase
Author: Lee Nam Jin
Author-email: nj@devhi.me
License: UNKNOWN
Download-URL: https://githur.com/rampart81/pyquibase/archive/1.0.tar.gz
Keywords: liquibase,db migration
Platform: UNKNOWN
Classifier: Programming Language :: Python :: 3
Classifier: Programming Language :: Python :: 3.2
Classifier: Programming Language :: Python :: 3.3
Classifier: Programming Language :: Python :: 3.4
Classifier: Programming Language :: Python :: 3.5
Classifier: Programming Language :: Python :: 3.6
Classifier: Programming Language :: Python :: 3.7
Requires-Python: >=3
